earthplot/__init__.py
earthplot/__main__.py
earthplot/earthplot.py
earthplot-0.1.6.dist-info/METADATA
earthplot-0.1.6.dist-info/WHEEL
earthplot-0.1.6.dist-info/entry_points.txt
earthplot-0.1.6.dist-info/top_level.txt
earthplot-0.1.6.dist-info/RECORD
