Metadata-Version: 2.1
Name: earthplot
Version: 0.1.6
Summary: UNKNOWN
Home-page: UNKNOWN
Author: UNKNOWN
Author-email: UNKNOWN
License: UNKNOWN
Platform: UNKNOWN
Requires-Dist: nctools
Requires-Dist: cartopy
Requires-Dist: pyloco (>=0.0.134)
Requires-Dist: Cartopy (>=0.17.0)
